golv/__init__.py
golv/agent.py
golv/client.py
golv/exeptions.py
golv/models.py
golv/setup_golv.py
golv-1.1.0.dist-info/licenses/LICENSE
golv-1.1.0.dist-info/METADATA
golv-1.1.0.dist-info/WHEEL
golv-1.1.0.dist-info/entry_points.txt
golv-1.1.0.dist-info/top_level.txt
golv-1.1.0.dist-info/RECORD
